skyCTF/Arithmetic.py
skyCTF/ContinuedFractions.py
skyCTF/MillerRabin.py
skyCTF/RSAvulnerableKeyGenerator.py
skyCTF/RSAwienerHacker.py
skyCTF/__init__.py
skyCTF/socialismCoreValue.py
skyCTF/vigenere.py
skyCTF_forgot_it-0.0.1.dist-info/LICENSE
skyCTF_forgot_it-0.0.1.dist-info/METADATA
skyCTF_forgot_it-0.0.1.dist-info/WHEEL
skyCTF_forgot_it-0.0.1.dist-info/top_level.txt
skyCTF_forgot_it-0.0.1.dist-info/RECORD
