Metadata-Version: 2.1
Name: skyCTF-forgot-it
Version: 0.0.1
Summary: some scripts collected from web
Home-page: https://gitee.com
Author: EricShen
Author-email: 87130495@qq.com
License: UNKNOWN
Platform: UNKNOWN
Classifier: Programming Language :: Python :: 3
Classifier: License :: OSI Approved :: MIT License
Classifier: Operating System :: OS Independent
Requires-Python: >=3.6
